florentino/__init__.py
florentino/__version__.py
florentino/linear_model/__init__.py
florentino/linear_model/linear.py
florentino/nn/__init__.py
florentino/nn/activation.py
florentino/nn/dense.py
florentino/nn/layer.py
florentino/nn/loss.py
florentino/nn/network.py
florentino/nn/softmax.py
florentino/nn/utillity.py
tests/__init__.py
tests/test_imports.py
florentino-0.0.0.1.dist-info/LICENSE.txt
florentino-0.0.0.1.dist-info/METADATA
florentino-0.0.0.1.dist-info/WHEEL
florentino-0.0.0.1.dist-info/top_level.txt
florentino-0.0.0.1.dist-info/RECORD
