Metadata-Version: 2.1
Name: florentino
Version: 0.0.0.1
Summary: I am obsessed with coding from scratch, so I only use Numpy for implementing this AI package.
Home-page: https://github.com/nguyenpanda
Author: Nguyen Tuong Ha
Maintainer: Florentino Developers
Maintainer-email: hatuongnguyen0107@gmail.com
License: Apache License 2.0
Project-URL: Source Code, https://github.com/nguyenpanda/florentino
Keywords: deeplearning machinelearning AI florentino hcmut bku
Classifier: Development Status :: 2 - Pre-Alpha
Classifier: License :: OSI Approved :: Apache Software License
Classifier: Operating System :: OS Independent
Classifier: Intended Audience :: Developers
Classifier: Intended Audience :: Education
Classifier: Intended Audience :: Science/Research
Classifier: Programming Language :: Python :: 3.9
Classifier: Programming Language :: Python :: 3.10
Classifier: Programming Language :: Python :: 3.11
Classifier: Programming Language :: Python :: 3.12
Classifier: Topic :: Software Development :: Libraries :: Python Modules
Requires-Python: >=3.9
License-File: LICENSE.txt
Requires-Dist: pip
Requires-Dist: numpy >=2.0.1
